Metadata-Version: 1.1
Name: django-embed
Version: 0.2
Summary: A simple Django app to generate embed code from youtube, twitter and slideshare.
Home-page: http://mejorando.la/
Author: https://github.com/mejorandola
Author-email: d@mejorando.la
License: MIT License
Keywords: Embed youtube twitter slideshare python
Platform: UNKNOWN
Classifier: Environment :: Web Environment
Classifier: Framework :: Django
Classifier: Intended Audience :: Developers
Classifier: License :: OSI Approved :: MIT License
Classifier: Operating System :: OS Independent
Classifier: Programming Language :: Python
Classifier: Programming Language :: Python :: 2.6
Classifier: Programming Language :: Python :: 2.7
Classifier: Topic :: Internet :: WWW/HTTP
Classifier: Topic :: Internet :: WWW/HTTP :: Dynamic Content
